additional_data/__init__.py
additional_data/additional_data_util.py
additional_data/adxml.py
additional_data/pdfmanipulator.py
additional_data/tests/__init__.py
additional_data/tests/test_ad_class.py
additional_data/tests/test_adutil_samples.py
additional_data-0.3.1.1.dist-info/LICENSE
additional_data-0.3.1.1.dist-info/METADATA
additional_data-0.3.1.1.dist-info/WHEEL
additional_data-0.3.1.1.dist-info/entry_points.txt
additional_data-0.3.1.1.dist-info/top_level.txt
additional_data-0.3.1.1.dist-info/RECORD
