Metadata-Version: 2.1
Name: additional-data
Version: 0.3.1.1
Summary: Simple library for reading and writing additional data files
Home-page: http://4s4u.de/additional_data/
Author: Andreas Starke
Author-email: andreas@4s4u.de
License: UNKNOWN
Platform: UNKNOWN
Classifier: Development Status :: 3 - Alpha
Classifier: Intended Audience :: Developers
Classifier: Operating System :: OS Independent
Classifier: License :: OSI Approved :: MIT License
Classifier: Programming Language :: Python :: 3
Classifier: Topic :: Software Development :: Libraries
Requires-Dist: PyPDF2
Requires-Dist: argparse
Requires-Dist: lxml
Requires-Dist: reportlab
